{
  "date" : "Thu, 05 Feb, 2026 23:48:03 +0000",
  "doco" : "For each file: start is seconds after start activity occurred. Length = milliseconds activity took",
  "files" : [
    {
      "name" : "/fsh-generated/resources/ImplementationGuide-xtehr.eu.ehds.models.json",
      "size" : 21103,
      "processes" : [
        {
          "activity" : "load",
          "start" : 40,
          "length" : 7
        },
        {
          "activity" : "checkR4R4B",
          "start" : 42,
          "length" : 10
        },
        {
          "activity" : "generateNarratives",
          "start" : 42,
          "length" : 61
        },
        {
          "activity" : "validate",
          "start" : 45,
          "length" : 1594
        },
        {
          "activity" : "generate1",
          "start" : 47,
          "length" : 93
        },
        {
          "activity" : "generate2",
          "start" : 55,
          "length" : 132
        },
        {
          "activity" : "generateValidationPack",
          "start" : 69,
          "length" : 8
        },
        {
          "activity" : "scanExamplesForR5",
          "start" : 86,
          "length" : 1
        }
      ]
    },
    {
      "name" : "fsh-generated/resources/StructureDefinition-EHDSAddress.json",
      "size" : 4008,
      "processes" : [
        {
          "activity" : "loadResources",
          "start" : 40,
          "length" : 7
        },
        {
          "activity" : "load",
          "start" : 40,
          "length" : 4
        },
        {
          "activity" : "generateSnapshots",
          "start" : 40,
          "length" : 7
        },
        {
          "activity" : "generateNarratives",
          "start" : 42,
          "length" : 59
        },
        {
          "activity" : "validate",
          "start" : 43,
          "length" : 309
        },
        {
          "activity" : "checkConformanceResources",
          "start" : 47,
          "length" : 1
        },
        {
          "activity" : "scanForUsageStats",
          "start" : 47,
          "length" : 1
        },
        {
          "activity" : "generate1",
          "start" : 47,
          "length" : 62
        },
        {
          "activity" : "generate2",
          "start" : 55,
          "length" : 926
        },
        {
          "activity" : "generate2",
          "start" : 61,
          "length" : 1045
        },
        {
          "activity" : "generateValidationPack",
          "start" : 69,
          "length" : 1
        },
        {
          "activity" : "scanProfilesForR5",
          "start" : 86,
          "length" : 1
        }
      ]
    },
    {
      "name" : "fsh-generated/resources/StructureDefinition-EHDSAdministeredDosage.json",
      "size" : 1417,
      "processes" : [
        {
          "activity" : "loadResources",
          "start" : 40,
          "length" : 2
        },
        {
          "activity" : "load",
          "start" : 40,
          "length" : 2
        },
        {
          "activity" : "generateSnapshots",
          "start" : 40,
          "length" : 39
        },
        {
          "activity" : "generateNarratives",
          "start" : 42,
          "length" : 15
        },
        {
          "activity" : "validate",
          "start" : 43,
          "length" : 145
        },
        {
          "activity" : "generate1",
          "start" : 47,
          "length" : 51
        },
        {
          "activity" : "generate2",
          "start" : 56,
          "length" : 145
        },
        {
          "activity" : "generate2",
          "start" : 62,
          "length" : 213
        },
        {
          "activity" : "generateValidationPack",
          "start" : 69,
          "length" : 4
        }
      ]
    },
    {
      "name" : "fsh-generated/resources/StructureDefinition-EHDSAdvanceDirective.json",
      "size" : 2800,
      "processes" : [
        {
          "activity" : "loadResources",
          "start" : 40,
          "length" : 3
        },
        {
          "activity" : "load",
          "start" : 40,
          "length" : 1
        },
        {
          "activity" : "generateSnapshots",
          "start" : 40,
          "length" : 30
        },
        {
          "activity" : "generateNarratives",
          "start" : 42,
          "length" : 12
        },
        {
          "activity" : "validate",
          "start" : 43,
          "length" : 52
        },
        {
          "activity" : "generate1",
          "start" : 47,
          "length" : 43
        },
        {
          "activity" : "generate2",
          "start" : 56,
          "length" : 128
        },
        {
          "activity" : "generate2",
          "start" : 62,
          "length" : 75
        },
        {
          "activity" : "generateValidationPack",
          "start" : 69,
          "length" : 1
        }
      ]
    },
    {
      "name" : "fsh-generated/resources/StructureDefinition-EHDSAlert.json",
      "size" : 5478,
      "processes" : [
        {
          "activity" : "loadResources",
          "start" : 40,
          "length" : 4
        },
        {
          "activity" : "load",
          "start" : 40,
          "length" : 2
        },
        {
          "activity" : "generateSnapshots",
          "start" : 40,
          "length" : 13
        },
        {
          "activity" : "generateNarratives",
          "start" : 42,
          "length" : 11
        },
        {
          "activity" : "validate",
          "start" : 43,
          "length" : 62
        },
        {
          "activity" : "generate1",
          "start" : 47,
          "length" : 61
        },
        {
          "activity" : "generate2",
          "start" : 56,
          "length" : 141
        },
        {
          "activity" : "generate2",
          "start" : 62,
          "length" : 65
        },
        {
          "activity" : "generateValidationPack",
          "start" : 69,
          "length" : 2
        }
      ]
    },
    {
      "name" : "fsh-generated/resources/StructureDefinition-EHDSAllergyIntolerance.json",
      "size" : 9415,
      "processes" : [
        {
          "activity" : "loadResources",
          "start" : 40,
          "length" : 5
        },
        {
          "activity" : "load",
          "start" : 40,
          "length" : 3
        },
        {
          "activity" : "generateSnapshots",
          "start" : 40,
          "length" : 21
        },
        {
          "activity" : "generateNarratives",
          "start" : 42,
          "length" : 12
        },
        {
          "activity" : "validate",
          "start" : 43,
          "length" : 87
        },
        {
          "activity" : "scanForUsageStats",
          "start" : 47,
          "length" : 1
        },
        {
          "activity" : "generate1",
          "start" : 47,
          "length" : 92
        },
        {
          "activity" : "generate2",
          "start" : 56,
          "length" : 181
        },
        {
          "activity" : "generate2",
          "start" : 62,
          "length" : 74
        },
        {
          "activity" : "generateValidationPack",
          "start" : 69,
          "length" : 7
        },
        {
          "activity" : "scanExamplesForR5",
          "start" : 86,
          "length" : 1
        }
      ]
    },
    {
      "name" : "fsh-generated/resources/StructureDefinition-EHDSAttachment.json",
      "size" : 3674,
      "processes" : [
        {
          "activity" : "loadResources",
          "start" : 40,
          "length" : 5
        },
        {
          "activity" : "load",
          "start" : 40,
          "length" : 3
        },
        {
          "activity" : "generateSnapshots",
          "start" : 40,
          "length" : 14
        },
        {
          "activity" : "generateNarratives",
          "start" : 42,
          "length" : 9
        },
        {
          "activity" : "validate",
          "start" : 43,
          "length" : 38
        },
        {
          "activity" : "generate1",
          "start" : 47,
          "length" : 41
        },
        {
          "activity" : "generate2",
          "start" : 56,
          "length" : 97
        },
        {
          "activity" : "generate2",
          "start" : 62,
          "length" : 40
        },
        {
          "activity" : "generateValidationPack",
          "start" : 69,
          "length" : 2
        }
      ]
    },
    {
      "name" : "fsh-generated/resources/StructureDefinition-EHDSBodyStructure.json",
      "size" : 3241,
      "processes" : [
        {
          "activity" : "loadResources",
          "start" : 40,
          "length" : 4
        },
        {
          "activity" : "load",
          "start" : 40,
          "length" : 2
        },
        {
          "activity" : "generateSnapshots",
          "start" : 40,
          "length" : 9
        },
        {
          "activity" : "generateNarratives",
          "start" : 42,
          "length" : 9
        },
        {
          "activity" : "validate",
          "start" : 43,
          "length" : 31
        },
        {
          "activity" : "generate1",
          "start" : 47,
          "length" : 38
        },
        {
          "activity" : "generate2",
          "start" : 57,
          "length" : 100
        },
        {
          "activity" : "generate2",
          "start" : 62,
          "length" : 37
        },
        {
          "activity" : "generateValidationPack",
          "start" : 69,
          "length" : 1
        }
      ]
    },
    {
      "name" : "fsh-generated/resources/StructureDefinition-EHDSCarePlan.json",
      "size" : 5020,
      "processes" : [
        {
          "activity" : "loadResources",
          "start" : 40,
          "length" : 5
        },
        {
          "activity" : "load",
          "start" : 40,
          "length" : 2
        },
        {
          "activity" : "load",
          "start" : 40,
          "length" : 1
        },
        {
          "activity" : "generateSnapshots",
          "start" : 40,
          "length" : 21
        },
        {
          "activity" : "load-configure",
          "start" : 42,
          "length" : 1
        },
        {
          "activity" : "generateNarratives",
          "start" : 42,
          "length" : 12
        },
        {
          "activity" : "validate",
          "start" : 43,
          "length" : 53
        },
        {
          "activity" : "generate1",
          "start" : 47,
          "length" : 77
        },
        {
          "activity" : "generate2",
          "start" : 57,
          "length" : 119
        },
        {
          "activity" : "generate2",
          "start" : 62,
          "length" : 53
        },
        {
          "activity" : "generateValidationPack",
          "start" : 69,
          "length" : 2
        }
      ]
    },
    {
      "name" : "fsh-generated/resources/StructureDefinition-EHDSCondition.json",
      "size" : 8518,
      "processes" : [
        {
          "activity" : "loadResources",
          "start" : 40,
          "length" : 5
        },
        {
          "activity" : "load",
          "start" : 40,
          "length" : 2
        },
        {
          "activity" : "generateSnapshots",
          "start" : 41,
          "length" : 20
        },
        {
          "activity" : "generateNarratives",
          "start" : 42,
          "length" : 18
        },
        {
          "activity" : "validate",
          "start" : 43,
          "length" : 69
        },
        {
          "activity" : "generate1",
          "start" : 47,
          "length" : 100
        },
        {
          "activity" : "generate2",
          "start" : 57,
          "length" : 192
        },
        {
          "activity" : "generate2",
          "start" : 62,
          "length" : 64
        },
        {
          "activity" : "generateValidationPack",
          "start" : 69,
          "length" : 3
        }
      ]
    },
    {
      "name" : "fsh-generated/resources/StructureDefinition-EHDSCurrentPregnancy.json",
      "size" : 3816,
      "processes" : [
        {
          "activity" : "loadResources",
          "start" : 40,
          "length" : 4
        },
        {
          "activity" : "load",
          "start" : 40,
          "length" : 2
        },
        {
          "activity" : "generateSnapshots",
          "start" : 41,
          "length" : 16
        },
        {
          "activity" : "generateNarratives",
          "start" : 42,
          "length" : 11
        },
        {
          "activity" : "validate",
          "start" : 43,
          "length" : 46
        },
        {
          "activity" : "generate1",
          "start" : 48,
          "length" : 54
        },
        {
          "activity" : "generate2",
          "start" : 57,
          "length" : 112
        },
        {
          "activity" : "generate2",
          "start" : 62,
          "length" : 57
        },
        {
          "activity" : "generateValidationPack",
          "start" : 69,
          "length" : 3
        },
        {
          "activity" : "scanExamplesForR5",
          "start" : 86,
          "length" : 1
        }
      ]
    },
    {
      "name" : "fsh-generated/resources/StructureDefinition-EHDSDataSet.json",
      "size" : 4822,
      "processes" : [
        {
          "activity" : "loadResources",
          "start" : 40,
          "length" : 5
        },
        {
          "activity" : "load",
          "start" : 40,
          "length" : 3
        },
        {
          "activity" : "generateNarratives",
          "start" : 42,
          "length" : 12
        },
        {
          "activity" : "validate",
          "start" : 44,
          "length" : 41
        },
        {
          "activity" : "generate1",
          "start" : 48,
          "length" : 56
        },
        {
          "activity" : "generate2",
          "start" : 57,
          "length" : 95
        },
        {
          "activity" : "generate2",
          "start" : 62,
          "length" : 40
        },
        {
          "activity" : "generateValidationPack",
          "start" : 69,
          "length" : 2
        }
      ]
    },
    {
      "name" : "fsh-generated/resources/StructureDefinition-EHDSDevice.json",
      "size" : 5800,
      "processes" : [
        {
          "activity" : "loadResources",
          "start" : 40,
          "length" : 5
        },
        {
          "activity" : "load",
          "start" : 40,
          "length" : 3
        },
        {
          "activity" : "generateSnapshots",
          "start" : 41,
          "length" : 16
        },
        {
          "activity" : "generateNarratives",
          "start" : 42,
          "length" : 11
        },
        {
          "activity" : "validate",
          "start" : 44,
          "length" : 54
        },
        {
          "activity" : "generate1",
          "start" : 48,
          "length" : 64
        },
        {
          "activity" : "generate2",
          "start" : 57,
          "length" : 107
        },
        {
          "activity" : "generate2",
          "start" : 62,
          "length" : 50
        },
        {
          "activity" : "generateValidationPack",
          "start" : 69,
          "length" : 3
        }
      ]
    },
    {
      "name" : "fsh-generated/resources/StructureDefinition-EHDSDeviceUse.json",
      "size" : 4549,
      "processes" : [
        {
          "activity" : "loadResources",
          "start" : 40,
          "length" : 4
        },
        {
          "activity" : "load",
          "start" : 40,
          "length" : 2
        },
        {
          "activity" : "generateSnapshots",
          "start" : 41,
          "length" : 16
        },
        {
          "activity" : "generateNarratives",
          "start" : 42,
          "length" : 8
        },
        {
          "activity" : "validate",
          "start" : 44,
          "length" : 47
        },
        {
          "activity" : "checkConformanceResources",
          "start" : 47,
          "length" : 1
        },
        {
          "activity" : "generate1",
          "start" : 48,
          "length" : 67
        },
        {
          "activity" : "generate2",
          "start" : 57,
          "length" : 109
        },
        {
          "activity" : "generate2",
          "start" : 62,
          "length" : 53
        },
        {
          "activity" : "generateValidationPack",
          "start" : 69,
          "length" : 1
        }
      ]
    },
    {
      "name" : "fsh-generated/resources/StructureDefinition-EHDSDischargeReport.json",
      "size" : 28463,
      "processes" : [
        {
          "activity" : "loadResources",
          "start" : 40,
          "length" : 10
        },
        {
          "activity" : "load",
          "start" : 40,
          "length" : 5
        },
        {
          "activity" : "generateSnapshots",
          "start" : 41,
          "length" : 53
        },
        {
          "activity" : "generateNarratives",
          "start" : 42,
          "length" : 30
        },
        {
          "activity" : "validate",
          "start" : 44,
          "length" : 179
        },
        {
          "activity" : "scanForUsageStats",
          "start" : 47,
          "length" : 1
        },
        {
          "activity" : "generate1",
          "start" : 48,
          "length" : 263
        },
        {
          "activity" : "generate2",
          "start" : 57,
          "length" : 263
        },
        {
          "activity" : "generate2",
          "start" : 62,
          "length" : 163
        },
        {
          "activity" : "makeDependencies",
          "start" : 65,
          "length" : 1
        },
        {
          "activity" : "generateValidationPack",
          "start" : 69,
          "length" : 7
        },
        {
          "activity" : "scanExamplesForR5",
          "start" : 86,
          "length" : 1
        }
      ]
    },
    {
      "name" : "fsh-generated/resources/StructureDefinition-EHDSDocument.json",
      "size" : 9560,
      "processes" : [
        {
          "activity" : "loadResources",
          "start" : 40,
          "length" : 6
        },
        {
          "activity" : "load",
          "start" : 40,
          "length" : 5
        },
        {
          "activity" : "generateNarratives",
          "start" : 42,
          "length" : 13
        },
        {
          "activity" : "validate",
          "start" : 44,
          "length" : 69
        },
        {
          "activity" : "generate1",
          "start" : 48,
          "length" : 112
        },
        {
          "activity" : "generate2",
          "start" : 58,
          "length" : 106
        },
        {
          "activity" : "generate2",
          "start" : 63,
          "length" : 63
        },
        {
          "activity" : "generateValidationPack",
          "start" : 69,
          "length" : 3
        }
      ]
    },
    {
      "name" : "fsh-generated/resources/StructureDefinition-EHDSDosage.json",
      "size" : 11402,
      "processes" : [
        {
          "activity" : "loadResources",
          "start" : 40,
          "length" : 6
        },
        {
          "activity" : "load",
          "start" : 40,
          "length" : 4
        },
        {
          "activity" : "generateNarratives",
          "start" : 42,
          "length" : 19
        },
        {
          "activity" : "validate",
          "start" : 44,
          "length" : 73
        },
        {
          "activity" : "generate1",
          "start" : 48,
          "length" : 121
        },
        {
          "activity" : "generate2",
          "start" : 58,
          "length" : 154
        },
        {
          "activity" : "generate2",
          "start" : 63,
          "length" : 54
        },
        {
          "activity" : "generateValidationPack",
          "start" : 69,
          "length" : 4
        }
      ]
    },
    {
      "name" : "fsh-generated/resources/StructureDefinition-EHDSEncounter.json",
      "size" : 11061,
      "processes" : [
        {
          "activity" : "loadResources",
          "start" : 40,
          "length" : 6
        },
        {
          "activity" : "load",
          "start" : 40,
          "length" : 4
        },
        {
          "activity" : "generateSnapshots",
          "start" : 41,
          "length" : 20
        },
        {
          "activity" : "generateNarratives",
          "start" : 42,
          "length" : 15
        },
        {
          "activity" : "validate",
          "start" : 44,
          "length" : 123
        },
        {
          "activity" : "scanForUsageStats",
          "start" : 47,
          "length" : 1
        },
        {
          "activity" : "generate1",
          "start" : 48,
          "length" : 139
        },
        {
          "activity" : "generate2",
          "start" : 58,
          "length" : 106
        },
        {
          "activity" : "generate2",
          "start" : 63,
          "length" : 59
        },
        {
          "activity" : "generateValidationPack",
          "start" : 69,
          "length" : 4
        }
      ]
    },
    {
      "name" : "fsh-generated/resources/StructureDefinition-EHDSEndpoint.json",
      "size" : 6291,
      "processes" : [
        {
          "activity" : "loadResources",
          "start" : 40,
          "length" : 4
        },
        {
          "activity" : "load",
          "start" : 40,
          "length" : 3
        },
        {
          "activity" : "generateSnapshots",
          "start" : 41,
          "length" : 16
        },
        {
          "activity" : "generateNarratives",
          "start" : 42,
          "length" : 8
        },
        {
          "activity" : "validate",
          "start" : 44,
          "length" : 27
        },
        {
          "activity" : "generate1",
          "start" : 48,
          "length" : 64
        },
        {
          "activity" : "generate2",
          "start" : 58,
          "length" : 62
        },
        {
          "activity" : "generate2",
          "start" : 63,
          "length" : 35
        },
        {
          "activity" : "generateValidationPack",
          "start" : 69,
          "length" : 1
        }
      ]
    },
    {
      "name" : "fsh-generated/resources/StructureDefinition-EHDSHealthProfessional.json",
      "size" : 6275,
      "processes" : [
        {
          "activity" : "loadResources",
          "start" : 40,
          "length" : 4
        },
        {
          "activity" : "load",
          "start" : 40,
          "length" : 57
        },
        {
          "activity" : "generateSnapshots",
          "start" : 41,
          "length" : 14
        },
        {
          "activity" : "load-configure",
          "start" : 42,
          "length" : 1
        },
        {
          "activity" : "generateNarratives",
          "start" : 42,
          "length" : 9
        },
        {
          "activity" : "validate",
          "start" : 44,
          "length" : 20
        },
        {
          "activity" : "generate1",
          "start" : 49,
          "length" : 61
        },
        {
          "activity" : "generate2",
          "start" : 58,
          "length" : 54
        },
        {
          "activity" : "generate2",
          "start" : 63,
          "length" : 31
        },
        {
          "activity" : "generateValidationPack",
          "start" : 69,
          "length" : 2
        },
        {
          "activity" : "scanExamplesForR5",
          "start" : 86,
          "length" : 1
        }
      ]
    },
    {
      "name" : "fsh-generated/resources/StructureDefinition-EHDSHumanName.json",
      "size" : 3165,
      "processes" : [
        {
          "activity" : "loadResources",
          "start" : 40,
          "length" : 4
        },
        {
          "activity" : "load",
          "start" : 40,
          "length" : 3
        },
        {
          "activity" : "generateSnapshots",
          "start" : 41,
          "length" : 9
        },
        {
          "activity" : "generateNarratives",
          "start" : 42,
          "length" : 8
        },
        {
          "activity" : "validate",
          "start" : 44,
          "length" : 17
        },
        {
          "activity" : "generate1",
          "start" : 49,
          "length" : 39
        },
        {
          "activity" : "generate2",
          "start" : 58,
          "length" : 48
        },
        {
          "activity" : "generate2",
          "start" : 63,
          "length" : 24
        }
      ]
    },
    {
      "name" : "fsh-generated/resources/StructureDefinition-EHDSImagingReport.json",
      "size" : 25918,
      "processes" : [
        {
          "activity" : "loadResources",
          "start" : 40,
          "length" : 9
        },
        {
          "activity" : "load",
          "start" : 40,
          "length" : 6
        },
        {
          "activity" : "generateSnapshots",
          "start" : 41,
          "length" : 21
        },
        {
          "activity" : "generateNarratives",
          "start" : 42,
          "length" : 33
        },
        {
          "activity" : "validate",
          "start" : 44,
          "length" : 92
        },
        {
          "activity" : "scanForUsageStats",
          "start" : 47,
          "length" : 1
        },
        {
          "activity" : "generate1",
          "start" : 49,
          "length" : 262
        },
        {
          "activity" : "generate2",
          "start" : 58,
          "length" : 185
        },
        {
          "activity" : "generate2",
          "start" : 63,
          "length" : 109
        },
        {
          "activity" : "generateValidationPack",
          "start" : 69,
          "length" : 7
        }
      ]
    },
    {
      "name" : "fsh-generated/resources/StructureDefinition-EHDSImagingStudy.json",
      "size" : 19143,
      "processes" : [
        {
          "activity" : "loadResources",
          "start" : 40,
          "length" : 7
        },
        {
          "activity" : "load",
          "start" : 40,
          "length" : 4
        },
        {
          "activity" : "generateSnapshots",
          "start" : 41,
          "length" : 14
        },
        {
          "activity" : "generateNarratives",
          "start" : 42,
          "length" : 27
        },
        {
          "activity" : "validate",
          "start" : 44,
          "length" : 67
        },
        {
          "activity" : "generate1",
          "start" : 49,
          "length" : 173
        },
        {
          "activity" : "generate2",
          "start" : 58,
          "length" : 126
        },
        {
          "activity" : "generate2",
          "start" : 63,
          "length" : 76
        },
        {
          "activity" : "generateValidationPack",
          "start" : 69,
          "length" : 4
        }
      ]
    },
    {
      "name" : "fsh-generated/resources/StructureDefinition-EHDSImmunisation.json",
      "size" : 5845,
      "processes" : [
        {
          "activity" : "loadResources",
          "start" : 40,
          "length" : 3
        },
        {
          "activity" : "load",
          "start" : 40,
          "length" : 3
        },
        {
          "activity" : "generateSnapshots",
          "start" : 41,
          "length" : 6
        },
        {
          "activity" : "generateNarratives",
          "start" : 42,
          "length" : 8
        },
        {
          "activity" : "validate",
          "start" : 44,
          "length" : 25
        },
        {
          "activity" : "generate1",
          "start" : 49,
          "length" : 62
        },
        {
          "activity" : "generate2",
          "start" : 58,
          "length" : 66
        },
        {
          "activity" : "generate2",
          "start" : 63,
          "length" : 34
        },
        {
          "activity" : "generateValidationPack",
          "start" : 69,
          "length" : 2
        }
      ]
    },
    {
      "name" : "fsh-generated/resources/StructureDefinition-EHDSLaboratoryObservation.json",
      "size" : 4486,
      "processes" : [
        {
          "activity" : "loadResources",
          "start" : 40,
          "length" : 4
        },
        {
          "activity" : "load",
          "start" : 40,
          "length" : 2
        },
        {
          "activity" : "generateSnapshots",
          "start" : 41,
          "length" : 40
        },
        {
          "activity" : "generateNarratives",
          "start" : 42,
          "length" : 9
        },
        {
          "activity" : "validate",
          "start" : 44,
          "length" : 64
        },
        {
          "activity" : "scanForUsageStats",
          "start" : 47,
          "length" : 1
        },
        {
          "activity" : "generate1",
          "start" : 49,
          "length" : 99
        },
        {
          "activity" : "generate2",
          "start" : 59,
          "length" : 155
        },
        {
          "activity" : "generate2",
          "start" : 63,
          "length" : 130
        },
        {
          "activity" : "generateValidationPack",
          "start" : 69,
          "length" : 3
        }
      ]
    },
    {
      "name" : "fsh-generated/resources/StructureDefinition-EHDSLaboratoryReport.json",
      "size" : 16787,
      "processes" : [
        {
          "activity" : "loadResources",
          "start" : 40,
          "length" : 9
        },
        {
          "activity" : "load",
          "start" : 40,
          "length" : 5
        },
        {
          "activity" : "generateSnapshots",
          "start" : 41,
          "length" : 14
        },
        {
          "activity" : "generateNarratives",
          "start" : 42,
          "length" : 17
        },
        {
          "activity" : "validate",
          "start" : 44,
          "length" : 70
        },
        {
          "activity" : "generate1",
          "start" : 49,
          "length" : 191
        },
        {
          "activity" : "generate2",
          "start" : 59,
          "length" : 129
        },
        {
          "activity" : "generate2",
          "start" : 63,
          "length" : 70
        },
        {
          "activity" : "generateValidationPack",
          "start" : 69,
          "length" : 5
        },
        {
          "activity" : "scanProfilesForR5",
          "start" : 86,
          "length" : 1
        },
        {
          "activity" : "scanExamplesForR5",
          "start" : 86,
          "length" : 1
        }
      ]
    },
    {
      "name" : "fsh-generated/resources/StructureDefinition-EHDSLocation.json",
      "size" : 3960,
      "processes" : [
        {
          "activity" : "loadResources",
          "start" : 40,
          "length" : 4
        },
        {
          "activity" : "load",
          "start" : 40,
          "length" : 2
        },
        {
          "activity" : "generateSnapshots",
          "start" : 41,
          "length" : 5
        },
        {
          "activity" : "generateNarratives",
          "start" : 42,
          "length" : 6
        },
        {
          "activity" : "validate",
          "start" : 44,
          "length" : 17
        },
        {
          "activity" : "checkConformanceResources2",
          "start" : 47,
          "length" : 1
        },
        {
          "activity" : "generate1",
          "start" : 49,
          "length" : 41
        },
        {
          "activity" : "generate2",
          "start" : 59,
          "length" : 54
        },
        {
          "activity" : "generate2",
          "start" : 63,
          "length" : 23
        },
        {
          "activity" : "generateValidationPack",
          "start" : 69,
          "length" : 1
        }
      ]
    },
    {
      "name" : "fsh-generated/resources/StructureDefinition-EHDSMedication.json",
      "size" : 17682,
      "processes" : [
        {
          "activity" : "loadResources",
          "start" : 40,
          "length" : 8
        },
        {
          "activity" : "load",
          "start" : 40,
          "length" : 5
        },
        {
          "activity" : "generateSnapshots",
          "start" : 41,
          "length" : 10
        },
        {
          "activity" : "generateNarratives",
          "start" : 42,
          "length" : 26
        },
        {
          "activity" : "validate",
          "start" : 44,
          "length" : 63
        },
        {
          "activity" : "checkConformanceResources",
          "start" : 47,
          "length" : 1
        },
        {
          "activity" : "scanForUsageStats",
          "start" : 47,
          "length" : 1
        },
        {
          "activity" : "generate1",
          "start" : 49,
          "length" : 174
        },
        {
          "activity" : "generate2",
          "start" : 59,
          "length" : 177
        },
        {
          "activity" : "generate2",
          "start" : 63,
          "length" : 48
        },
        {
          "activity" : "generateValidationPack",
          "start" : 69,
          "length" : 4
        }
      ]
    },
    {
      "name" : "fsh-generated/resources/StructureDefinition-EHDSMedicationAdministration.json",
      "size" : 4341,
      "processes" : [
        {
          "activity" : "loadResources",
          "start" : 40,
          "length" : 4
        },
        {
          "activity" : "load",
          "start" : 40,
          "length" : 2
        },
        {
          "activity" : "generateSnapshots",
          "start" : 41,
          "length" : 5
        },
        {
          "activity" : "generateNarratives",
          "start" : 42,
          "length" : 11
        },
        {
          "activity" : "validate",
          "start" : 45,
          "length" : 24
        },
        {
          "activity" : "generate1",
          "start" : 50,
          "length" : 64
        },
        {
          "activity" : "generate2",
          "start" : 59,
          "length" : 71
        },
        {
          "activity" : "generate2",
          "start" : 63,
          "length" : 30
        },
        {
          "activity" : "generateValidationPack",
          "start" : 69,
          "length" : 2
        }
      ]
    },
    {
      "name" : "fsh-generated/resources/StructureDefinition-EHDSMedicationDispense.json",
      "size" : 7467,
      "processes" : [
        {
          "activity" : "loadResources",
          "start" : 40,
          "length" : 4
        },
        {
          "activity" : "load",
          "start" : 40,
          "length" : 3
        },
        {
          "activity" : "generateSnapshots",
          "start" : 41,
          "length" : 5
        },
        {
          "activity" : "generateNarratives",
          "start" : 42,
          "length" : 10
        },
        {
          "activity" : "validate",
          "start" : 45,
          "length" : 29
        },
        {
          "activity" : "generate1",
          "start" : 50,
          "length" : 84
        },
        {
          "activity" : "generate2",
          "start" : 59,
          "length" : 80
        },
        {
          "activity" : "generate2",
          "start" : 63,
          "length" : 33
        },
        {
          "activity" : "generateValidationPack",
          "start" : 69,
          "length" : 2
        }
      ]
    },
    {
      "name" : "fsh-generated/resources/StructureDefinition-EHDSMedicationPrescription.json",
      "size" : 17497,
      "processes" : [
        {
          "activity" : "loadResources",
          "start" : 40,
          "length" : 7
        },
        {
          "activity" : "load",
          "start" : 40,
          "length" : 4
        },
        {
          "activity" : "generateSnapshots",
          "start" : 41,
          "length" : 8
        },
        {
          "activity" : "load-configure",
          "start" : 42,
          "length" : 1
        },
        {
          "activity" : "generateNarratives",
          "start" : 42,
          "length" : 16
        },
        {
          "activity" : "validate",
          "start" : 45,
          "length" : 55
        },
        {
          "activity" : "generate1",
          "start" : 50,
          "length" : 182
        },
        {
          "activity" : "generate2",
          "start" : 59,
          "length" : 105
        },
        {
          "activity" : "generate2",
          "start" : 63,
          "length" : 49
        },
        {
          "activity" : "generateValidationPack",
          "start" : 69,
          "length" : 4
        }
      ]
    },
    {
      "name" : "fsh-generated/resources/StructureDefinition-EHDSMedicationUse.json",
      "size" : 5308,
      "processes" : [
        {
          "activity" : "loadResources",
          "start" : 40,
          "length" : 5
        },
        {
          "activity" : "load",
          "start" : 40,
          "length" : 2
        },
        {
          "activity" : "generateSnapshots",
          "start" : 41,
          "length" : 4
        },
        {
          "activity" : "generateNarratives",
          "start" : 42,
          "length" : 7
        },
        {
          "activity" : "validate",
          "start" : 45,
          "length" : 26
        },
        {
          "activity" : "generate1",
          "start" : 50,
          "length" : 71
        },
        {
          "activity" : "generate2",
          "start" : 59,
          "length" : 68
        },
        {
          "activity" : "generate2",
          "start" : 64,
          "length" : 31
        },
        {
          "activity" : "generateValidationPack",
          "start" : 69,
          "length" : 2
        }
      ]
    },
    {
      "name" : "fsh-generated/resources/StructureDefinition-EHDSObservation.json",
      "size" : 29084,
      "processes" : [
        {
          "activity" : "loadResources",
          "start" : 40,
          "length" : 10
        },
        {
          "activity" : "load",
          "start" : 40,
          "length" : 7
        },
        {
          "activity" : "generateNarratives",
          "start" : 42,
          "length" : 106
        },
        {
          "activity" : "validate",
          "start" : 45,
          "length" : 101
        },
        {
          "activity" : "scanForUsageStats",
          "start" : 47,
          "length" : 1
        },
        {
          "activity" : "generate1",
          "start" : 50,
          "length" : 313
        },
        {
          "activity" : "generate2",
          "start" : 59,
          "length" : 206
        },
        {
          "activity" : "generate2",
          "start" : 64,
          "length" : 72
        },
        {
          "activity" : "generateValidationPack",
          "start" : 69,
          "length" : 11
        }
      ]
    },
    {
      "name" : "fsh-generated/resources/StructureDefinition-EHDSOrganisation.json",
      "size" : 3264,
      "processes" : [
        {
          "activity" : "loadResources",
          "start" : 40,
          "length" : 4
        },
        {
          "activity" : "load",
          "start" : 40,
          "length" : 2
        },
        {
          "activity" : "generateSnapshots",
          "start" : 41,
          "length" : 2
        },
        {
          "activity" : "generateNarratives",
          "start" : 42,
          "length" : 9
        },
        {
          "activity" : "validate",
          "start" : 45,
          "length" : 15
        },
        {
          "activity" : "generate1",
          "start" : 50,
          "length" : 37
        },
        {
          "activity" : "generate2",
          "start" : 60,
          "length" : 48
        },
        {
          "activity" : "generate2",
          "start" : 64,
          "length" : 19
        },
        {
          "activity" : "generateValidationPack",
          "start" : 69,
          "length" : 2
        }
      ]
    },
    {
      "name" : "fsh-generated/resources/StructureDefinition-EHDSPatient.json",
      "size" : 4183,
      "processes" : [
        {
          "activity" : "loadResources",
          "start" : 40,
          "length" : 4
        },
        {
          "activity" : "load",
          "start" : 40,
          "length" : 2
        },
        {
          "activity" : "generateSnapshots",
          "start" : 41,
          "length" : 2
        },
        {
          "activity" : "generateNarratives",
          "start" : 43,
          "length" : 9
        },
        {
          "activity" : "validate",
          "start" : 45,
          "length" : 16
        },
        {
          "activity" : "scanForUsageStats",
          "start" : 47,
          "length" : 1
        },
        {
          "activity" : "generate1",
          "start" : 50,
          "length" : 47
        },
        {
          "activity" : "generate2",
          "start" : 60,
          "length" : 55
        },
        {
          "activity" : "generate2",
          "start" : 64,
          "length" : 18
        },
        {
          "activity" : "generateValidationPack",
          "start" : 69,
          "length" : 1
        },
        {
          "activity" : "scanExamplesForR5",
          "start" : 86,
          "length" : 1
        }
      ]
    },
    {
      "name" : "fsh-generated/resources/StructureDefinition-EHDSPatientSummary.json",
      "size" : 33251,
      "processes" : [
        {
          "activity" : "loadResources",
          "start" : 40,
          "length" : 11
        },
        {
          "activity" : "load",
          "start" : 40,
          "length" : 9
        },
        {
          "activity" : "generateSnapshots",
          "start" : 41,
          "length" : 16
        },
        {
          "activity" : "generateNarratives",
          "start" : 43,
          "length" : 32
        },
        {
          "activity" : "validate",
          "start" : 45,
          "length" : 163
        },
        {
          "activity" : "scanForUsageStats",
          "start" : 47,
          "length" : 1
        },
        {
          "activity" : "generate1",
          "start" : 50,
          "length" : 298
        },
        {
          "activity" : "generate2",
          "start" : 60,
          "length" : 211
        },
        {
          "activity" : "generate2",
          "start" : 64,
          "length" : 113
        },
        {
          "activity" : "generateValidationPack",
          "start" : 69,
          "length" : 10
        }
      ]
    },
    {
      "name" : "fsh-generated/resources/StructureDefinition-EHDSPregnancyHistory.json",
      "size" : 3036,
      "processes" : [
        {
          "activity" : "loadResources",
          "start" : 40,
          "length" : 4
        },
        {
          "activity" : "load",
          "start" : 40,
          "length" : 3
        },
        {
          "activity" : "generateSnapshots",
          "start" : 41,
          "length" : 4
        },
        {
          "activity" : "generateNarratives",
          "start" : 43,
          "length" : 6
        },
        {
          "activity" : "validate",
          "start" : 45,
          "length" : 20
        },
        {
          "activity" : "generate1",
          "start" : 51,
          "length" : 45
        },
        {
          "activity" : "generate2",
          "start" : 60,
          "length" : 58
        },
        {
          "activity" : "generate2",
          "start" : 64,
          "length" : 27
        },
        {
          "activity" : "generateValidationPack",
          "start" : 69,
          "length" : 1
        }
      ]
    },
    {
      "name" : "fsh-generated/resources/StructureDefinition-EHDSProcedure.json",
      "size" : 7813,
      "processes" : [
        {
          "activity" : "loadResources",
          "start" : 40,
          "length" : 4
        },
        {
          "activity" : "load",
          "start" : 40,
          "length" : 3
        },
        {
          "activity" : "generateSnapshots",
          "start" : 41,
          "length" : 4
        },
        {
          "activity" : "generateNarratives",
          "start" : 43,
          "length" : 14
        },
        {
          "activity" : "validate",
          "start" : 45,
          "length" : 30
        },
        {
          "activity" : "generate1",
          "start" : 51,
          "length" : 91
        },
        {
          "activity" : "generate2",
          "start" : 60,
          "length" : 167
        },
        {
          "activity" : "generate2",
          "start" : 64,
          "length" : 36
        },
        {
          "activity" : "generateValidationPack",
          "start" : 69,
          "length" : 2
        }
      ]
    },
    {
      "name" : "fsh-generated/resources/StructureDefinition-EHDSRelatedPerson.json",
      "size" : 3810,
      "processes" : [
        {
          "activity" : "loadResources",
          "start" : 40,
          "length" : 4
        },
        {
          "activity" : "load",
          "start" : 40,
          "length" : 2
        },
        {
          "activity" : "generateSnapshots",
          "start" : 41,
          "length" : 3
        },
        {
          "activity" : "generateNarratives",
          "start" : 43,
          "length" : 7
        },
        {
          "activity" : "validate",
          "start" : 45,
          "length" : 13
        },
        {
          "activity" : "generate1",
          "start" : 51,
          "length" : 39
        },
        {
          "activity" : "generate2",
          "start" : 60,
          "length" : 87
        },
        {
          "activity" : "generate2",
          "start" : 64,
          "length" : 20
        },
        {
          "activity" : "generateValidationPack",
          "start" : 69,
          "length" : 1
        }
      ]
    },
    {
      "name" : "fsh-generated/resources/StructureDefinition-EHDSServiceRequest.json",
      "size" : 7018,
      "processes" : [
        {
          "activity" : "loadResources",
          "start" : 40,
          "length" : 4
        },
        {
          "activity" : "load",
          "start" : 40,
          "length" : 3
        },
        {
          "activity" : "generateSnapshots",
          "start" : 41,
          "length" : 4
        },
        {
          "activity" : "generateNarratives",
          "start" : 43,
          "length" : 11
        },
        {
          "activity" : "validate",
          "start" : 45,
          "length" : 31
        },
        {
          "activity" : "generate1",
          "start" : 51,
          "length" : 92
        },
        {
          "activity" : "generate2",
          "start" : 60,
          "length" : 126
        },
        {
          "activity" : "generate2",
          "start" : 64,
          "length" : 38
        },
        {
          "activity" : "generateValidationPack",
          "start" : 69,
          "length" : 2
        }
      ]
    },
    {
      "name" : "fsh-generated/resources/StructureDefinition-EHDSSpecimen.json",
      "size" : 10825,
      "processes" : [
        {
          "activity" : "loadResources",
          "start" : 40,
          "length" : 5
        },
        {
          "activity" : "load",
          "start" : 40,
          "length" : 3
        },
        {
          "activity" : "generateSnapshots",
          "start" : 41,
          "length" : 7
        },
        {
          "activity" : "load-configure",
          "start" : 42,
          "length" : 1
        },
        {
          "activity" : "generateNarratives",
          "start" : 43,
          "length" : 16
        },
        {
          "activity" : "validate",
          "start" : 45,
          "length" : 38
        },
        {
          "activity" : "generate1",
          "start" : 51,
          "length" : 117
        },
        {
          "activity" : "generate2",
          "start" : 60,
          "length" : 140
        },
        {
          "activity" : "generate2",
          "start" : 64,
          "length" : 34
        },
        {
          "activity" : "generateValidationPack",
          "start" : 69,
          "length" : 3
        }
      ]
    },
    {
      "name" : "fsh-generated/resources/StructureDefinition-EHDSTelecom.json",
      "size" : 1855,
      "processes" : [
        {
          "activity" : "loadResources",
          "start" : 40,
          "length" : 3
        },
        {
          "activity" : "load",
          "start" : 40,
          "length" : 2
        },
        {
          "activity" : "generateSnapshots",
          "start" : 41,
          "length" : 3
        },
        {
          "activity" : "generateNarratives",
          "start" : 43,
          "length" : 4
        },
        {
          "activity" : "validate",
          "start" : 45,
          "length" : 10
        },
        {
          "activity" : "generate1",
          "start" : 51,
          "length" : 25
        },
        {
          "activity" : "generate2",
          "start" : 60,
          "length" : 58
        },
        {
          "activity" : "generate2",
          "start" : 64,
          "length" : 15
        },
        {
          "activity" : "generateValidationPack",
          "start" : 69,
          "length" : 2
        }
      ]
    },
    {
      "name" : "fsh-generated/resources/StructureDefinition-EHDSTravelHistory.json",
      "size" : 1746,
      "processes" : [
        {
          "activity" : "loadResources",
          "start" : 40,
          "length" : 3
        },
        {
          "activity" : "load",
          "start" : 40,
          "length" : 2
        },
        {
          "activity" : "generateSnapshots",
          "start" : 41,
          "length" : 5
        },
        {
          "activity" : "generateNarratives",
          "start" : 43,
          "length" : 5
        },
        {
          "activity" : "validate",
          "start" : 45,
          "length" : 15
        },
        {
          "activity" : "scanForUsageStats",
          "start" : 47,
          "length" : 1
        },
        {
          "activity" : "generate1",
          "start" : 51,
          "length" : 28
        },
        {
          "activity" : "generate2",
          "start" : 61,
          "length" : 87
        },
        {
          "activity" : "generate2",
          "start" : 64,
          "length" : 23
        },
        {
          "activity" : "generateValidationPack",
          "start" : 69,
          "length" : 1
        }
      ]
    },
    {
      "name" : "/input/includes/dmn2html.xslt",
      "size" : 6208
    },
    {
      "name" : "/input/includes/dmn.css",
      "size" : 838,
      "processes" : [
        {
          "activity" : "generate2",
          "start" : 64,
          "length" : 1
        }
      ]
    },
    {
      "name" : "/fsh-generated/includes/fsh-link-references.md",
      "size" : 2611,
      "processes" : [
        {
          "activity" : "generate2",
          "start" : 61,
          "length" : 1
        }
      ]
    },
    {
      "name" : "/fsh-generated/includes/menu.xml",
      "size" : 2478
    },
    {
      "name" : "/input/pagecontent/useCaseLabOrder.md",
      "size" : 746
    },
    {
      "name" : "/input/pagecontent/obligationsLabReport.md",
      "size" : 1060
    },
    {
      "name" : "/input/pagecontent/StructureDefinition-EHDSLaboratoryObservation-intro.md",
      "size" : 3135
    },
    {
      "name" : "/input/pagecontent/StructureDefinition-EHDSPatientSummary-intro.md",
      "size" : 1322
    },
    {
      "name" : "/input/pagecontent/howto.md",
      "size" : 8792,
      "processes" : [
        {
          "activity" : "generate2",
          "start" : 61,
          "length" : 1
        }
      ]
    },
    {
      "name" : "/input/pagecontent/StructureDefinition-EHDSPatientSummary-notes.md",
      "size" : 1816
    },
    {
      "name" : "/input/pagecontent/useCaseDispensation.md",
      "size" : 3541
    },
    {
      "name" : "/input/pagecontent/useCasePatientSummary.md",
      "size" : 1649
    },
    {
      "name" : "/input/pagecontent/useCasePrescription.md",
      "size" : 3370
    },
    {
      "name" : "/input/pagecontent/knownIssues.md",
      "size" : 128
    },
    {
      "name" : "/input/pagecontent/StructureDefinition-EHDSDosaging-notes.md",
      "size" : 2846
    },
    {
      "name" : "/input/pagecontent/useCaseHospitalDischargeReport.md",
      "size" : 1131
    },
    {
      "name" : "/input/pagecontent/useCaseLabReport.md",
      "size" : 1663
    },
    {
      "name" : "/input/pagecontent/scope.md",
      "size" : 1974
    },
    {
      "name" : "/input/pagecontent/useCaseMedicalImages.md",
      "size" : 1011
    },
    {
      "name" : "/input/pagecontent/StructureDefinition-EHDSObservation-intro.md",
      "size" : 3023,
      "processes" : [
        {
          "activity" : "generate2",
          "start" : 61,
          "length" : 1
        }
      ]
    },
    {
      "name" : "/input/pagecontent/downloads.md",
      "size" : 299
    },
    {
      "name" : "/input/pagecontent/index.md",
      "size" : 3700
    },
    {
      "name" : "/input/pagecontent/wow.md",
      "size" : 1067
    },
    {
      "name" : "/template/config",
      "size" : 0
    },
    {
      "name" : "/template/config/_config.yml",
      "size" : 140
    },
    {
      "name" : "/input/images",
      "size" : 0
    },
    {
      "name" : "/input/images/24px.svg",
      "size" : 234
    },
    {
      "name" : "/temp/pages/_includes/artifacts.xml",
      "size" : 23867,
      "processes" : [
        {
          "activity" : "generate2",
          "start" : 61,
          "length" : 1
        }
      ]
    }
  ]
}
